entryexiterrorlogging.py
entryexiterrorlogging-0.0.3.dist-info/LICENSE
entryexiterrorlogging-0.0.3.dist-info/METADATA
entryexiterrorlogging-0.0.3.dist-info/WHEEL
entryexiterrorlogging-0.0.3.dist-info/top_level.txt
entryexiterrorlogging-0.0.3.dist-info/RECORD
